fpng/__init__.py
fpng/_version.py
fpng/fpng_ext.cp310-win_amd64.pyd
fpng-0.1.0.dist-info/METADATA
fpng-0.1.0.dist-info/WHEEL
fpng-0.1.0.dist-info/licenses/LICENSE.txt
fpng-0.1.0.dist-info/RECORD
