Metadata-Version: 2.1
Name: fpng
Version: 0.1.0
Summary: Very fast .PNG image writer for Python
Keywords: PNG
Author: KEUM Myungchul
Classifier: Development Status :: 3 - Alpha
Classifier: Topic :: Multimedia :: Graphics
Classifier: Topic :: Multimedia :: Graphics :: Graphics Conversion
Classifier: License :: OSI Approved :: MIT License
Classifier: Programming Language :: C++
Classifier: Programming Language :: Python :: 3
Project-URL: Homepage, https://github.com/dofuuz/py-fpng-nb
Requires-Python: >=3.8
Requires-Dist: lazy_loader
Requires-Dist: pytest; extra == "test"
Requires-Dist: opencv_python; extra == "test"
Requires-Dist: numpy; extra == "test"
Requires-Dist: Pillow; extra == "test"
Provides-Extra: test
